pyBlindRL/__init__.py
pyBlindRL/commands.py
pyblindrl-0.1.0.dist-info/LICENSE
pyblindrl-0.1.0.dist-info/WHEEL
pyblindrl-0.1.0.dist-info/METADATA
pyblindrl-0.1.0.dist-info/RECORD
